duckypass/__init__.py
duckypass/duckypass.py
duckypass-1.0.4.dist-info/licenses/LICENSE
duckypass-1.0.4.dist-info/METADATA
duckypass-1.0.4.dist-info/WHEEL
duckypass-1.0.4.dist-info/top_level.txt
duckypass-1.0.4.dist-info/RECORD
