Metadata-Version: 2.4
Name: DuckyPass
Version: 1.0.4
Summary: A Python module for generating passwords using the DuckyPass API.
Home-page: https://github.com/maxrhys/PythonDuckyPassAPI
Author: Rhys Wills
Author-email: Rhys Wills <rhys@rwills.net>
License: gpl3
Keywords: password,generator,API,DuckyPass
Classifier: Programming Language :: Python :: 3
Classifier: License :: OSI Approved :: GNU General Public License v3 (GPLv3)
Classifier: Operating System :: OS Independent
License-File: LICENSE
Dynamic: author
Dynamic: home-page
Dynamic: license-file
